comp11.v
module compl1(output wire [3:0] Out, input wire [3:0] Inp, input wire cpl);
    assign Out = cpl ? ~Inp : Inp;   
endmodule

testbench/compl1_exhaustive_tb.v
`timescale 1ns/1ps

module tb_compl1_exhaustive;
    reg [3:0] Inp;
    reg cpl;
    wire [3:0] Out;

    integer i;
    integer errors;
    integer checks;
    reg [3:0] expected;

    // Instantiate unit under test
    compl1 uut(.Out(Out), .Inp(Inp), .cpl(cpl));

    initial begin
    $dumpfile("vcd/compl1_exhaustive_tb.vcd");
    // Dump only the signals we care about to keep the VCD compact
    $dumpvars(0, tb_compl1_exhaustive.Inp, tb_compl1_exhaustive.cpl, tb_compl1_exhaustive.Out);

        errors = 0;
        checks = 0;

        for (i = 0; i < 16; i = i + 1) begin
            Inp = i[3:0];

            // cpl = 0 -> Out should equal Inp
            cpl = 0; #10;
            checks = checks + 1;
            if (Out !== Inp) begin
                $display("%0t ERROR: Inp=%b cpl=0 Out=%b expected=%b", $time, Inp, Out, Inp);
                errors = errors + 1;
            end else begin
                $display("%0t OK: Inp=%b cpl=0 Out=%b", $time, Inp, Out);
            end

            // cpl = 1 -> Out should be two's complement: (~Inp) + 1
            cpl = 1; #10;
            checks = checks + 1;
            // Module implements one's complement when cpl==1 (Out = ~Inp)
            expected = ~Inp;
            if (Out !== expected) begin
                $display("%0t ERROR: Inp=%b cpl=1 Out=%b expected=%b", $time, Inp, Out, expected);
                errors = errors + 1;
            end else begin
                $display("%0t OK: Inp=%b cpl=1 Out=%b (expected=%b)", $time, Inp, Out, expected);
            end
        end

        $display("Compl1 exhaustive test finished: %0d checks, %0d errors", checks, errors);
        $finish;
    end

endmodule

vcd/compl1_exhaustive_tb.vcd
$date
	Sun Oct 12 11:09:10 2025
$end
$version
	Icarus Verilog
$end
$timescale
	1ps
$end
$scope module tb_compl1_exhaustive $end
$var reg 4 ! Inp [3:0] $end
$upscope $end
$scope module tb_compl1_exhaustive $end
$var reg 1 " cpl $end
$upscope $end
$scope module tb_compl1_exhaustive $end
$var wire 4 # Out [3:0] $end
$upscope $end
$enddefinitions $end
$comment Show the parameter values. $end
$dumpall
$end
#0
$dumpvars
b0 #
0"
b0 !
$end
#10000
b1111 #
1"
#20000
b1 #
0"
b1 !
#30000
b1110 #
1"
#40000
b10 #
0"
b10 !
#50000
b1101 #
1"
#60000
b11 #
0"
b11 !
#70000
b1100 #
1"
#80000
b100 #
0"
b100 !
#90000
b1011 #
1"
#100000
b101 #
0"
b101 !
#110000
b1010 #
1"
#120000
b110 #
0"
b110 !
#130000
b1001 #
1"
#140000
b111 #
0"
b111 !
#150000
b1000 #
1"
#160000
0"
b1000 !
#170000
b111 #
1"
#180000
b1001 #
0"
b1001 !
#190000
b110 #
1"
#200000
b1010 #
0"
b1010 !
#210000
b101 #
1"
#220000
b1011 #
0"
b1011 !
#230000
b100 #
1"
#240000
b1100 #
0"
b1100 !
#250000
b11 #
1"
#260000
b1101 #
0"
b1101 !
#270000
b10 #
1"
#280000
b1110 #
0"
b1110 !
#290000
b1 #
1"
#300000
b1111 #
0"
b1111 !
#310000
b0 #
1"
