mux2_4.v
// Multiplexor 2 a 1 de 4 bits
// Selecciona entre las entradas A y B según el selector s
module mux2_4(
    output wire [3:0] Out, // Salida de 4 bits
    input wire [3:0] A,    // Entrada A
    input wire [3:0] B,    // Entrada B
    input wire s           // Selector: 0 para A, 1 para B
);
    assign Out = s ? B : A; // Selección de salida
endmodule

testbench/mux2_4_exhaustive_tb.v
`timescale 1ns/1ps

module tb_mux2_4_exhaustive;
    reg [3:0] A;
    reg [3:0] B;
    reg s;
    wire [3:0] Out;

    integer i;
    integer errors;
    integer checks;

    // Instantiate unit under test
    mux2_4 uut(.Out(Out), .A(A), .B(B), .s(s));

    initial begin
        $dumpfile("vcd/mux2_4_exhaustive_tb.vcd");
        $dumpvars(0, tb_mux2_4_exhaustive);

        errors = 0;
        checks = 0;

        // Iterate all 4-bit combinations for A
        for (i = 0; i < 16; i = i + 1) begin
            A = i[3:0];
            // B is ones' complement of A (invert all bits)
            B = ~A;

            // First, s = 0 -> Out should be A
            s = 0; #10;
            checks = checks + 1;
            if (Out !== A) begin
                $display("%0t ERROR: A=%b s=0 Out=%b expected=%b", $time, A, Out, A);
                errors = errors + 1;
            end else begin
                $display("%0t OK: A=%b s=0 Out=%b", $time, A, Out);
            end

            // Then, s = 1 -> Out should be B (ones' complement)
            s = 1; #10;
            checks = checks + 1;
            if (Out !== B) begin
                $display("%0t ERROR: A=%b s=1 Out=%b expected=%b", $time, A, Out, B);
                errors = errors + 1;
            end else begin
                $display("%0t OK: A=%b s=1 Out=%b (B=%b)", $time, A, Out, B);
            end
        end

        $display("Exhaustive test finished: %0d checks, %0d errors", checks, errors);
        $finish;
    end

endmodule

vcd/mux2_4_exhaustive_tb.vcd
$date
	Sun Oct 12 11:00:37 2025
$end
$version
	Icarus Verilog
$end
$timescale
	1ps
$end
$scope module tb_mux2_4_exhaustive $end
$var wire 4 ! Out [3:0] $end
$var reg 4 " A [3:0] $end
$var reg 4 # B [3:0] $end
$var reg 1 $ s $end
$var integer 32 % checks [31:0] $end
$var integer 32 & errors [31:0] $end
$var integer 32 ' i [31:0] $end
$scope module uut $end
$var wire 4 ( A [3:0] $end
$var wire 4 ) B [3:0] $end
$var wire 1 $ s $end
$var wire 4 * Out [3:0] $end
$upscope $end
$upscope $end
$enddefinitions $end
$comment Show the parameter values. $end
$dumpall
$end
#0
$dumpvars
b0 *
b1111 )
b0 (
b0 '
b0 &
b0 %
0$
b1111 #
b0 "
b0 !
$end
#10000
b1111 !
b1111 *
1$
b1 %
#20000
b1 !
b1 *
0$
b1110 #
b1110 )
b1 "
b1 (
b1 '
b10 %
#30000
b1110 !
b1110 *
1$
b11 %
#40000
b10 !
b10 *
0$
b1101 #
b1101 )
b10 "
b10 (
b10 '
b100 %
#50000
b1101 !
b1101 *
1$
b101 %
#60000
b11 !
b11 *
0$
b1100 #
b1100 )
b11 "
b11 (
b11 '
b110 %
#70000
b1100 !
b1100 *
1$
b111 %
#80000
b100 !
b100 *
0$
b1011 #
b1011 )
b100 "
b100 (
b100 '
b1000 %
#90000
b1011 !
b1011 *
1$
b1001 %
#100000
b101 !
b101 *
0$
b1010 #
b1010 )
b101 "
b101 (
b101 '
b1010 %
#110000
b1010 !
b1010 *
1$
b1011 %
#120000
b110 !
b110 *
0$
b1001 #
b1001 )
b110 "
b110 (
b110 '
b1100 %
#130000
b1001 !
b1001 *
1$
b1101 %
#140000
b111 !
b111 *
0$
b1000 #
b1000 )
b111 "
b111 (
b111 '
b1110 %
#150000
b1000 !
b1000 *
1$
b1111 %
#160000
0$
b111 #
b111 )
b1000 "
b1000 (
b1000 '
b10000 %
#170000
b111 !
b111 *
1$
b10001 %
#180000
b1001 !
b1001 *
0$
b110 #
b110 )
b1001 "
b1001 (
b1001 '
b10010 %
#190000
b110 !
b110 *
1$
b10011 %
#200000
b1010 !
b1010 *
0$
b101 #
b101 )
b1010 "
b1010 (
b1010 '
b10100 %
#210000
b101 !
b101 *
1$
b10101 %
#220000
b1011 !
b1011 *
0$
b100 #
b100 )
b1011 "
b1011 (
b1011 '
b10110 %
#230000
b100 !
b100 *
1$
b10111 %
#240000
b1100 !
b1100 *
0$
b11 #
b11 )
b1100 "
b1100 (
b1100 '
b11000 %
#250000
b11 !
b11 *
1$
b11001 %
#260000
b1101 !
b1101 *
0$
b10 #
b10 )
b1101 "
b1101 (
b1101 '
b11010 %
#270000
b10 !
b10 *
1$
b11011 %
#280000
b1110 !
b1110 *
0$
b1 #
b1 )
b1110 "
b1110 (
b1110 '
b11100 %
#290000
b1 !
b1 *
1$
b11101 %
#300000
b1111 !
b1111 *
0$
b0 #
b0 )
b1111 "
b1111 (
b1111 '
b11110 %
#310000
b0 !
b0 *
1$
b11111 %
#320000
b10000 '
b100000 %
