mux2_4.v
// Multiplexor 2 a 1 de 4 bits
// Selecciona entre las entradas A y B según el selector s
module mux2_4(
    output wire [3:0] Out, // Salida de 4 bits
    input wire [3:0] A,    // Entrada A
    input wire [3:0] B,    // Entrada B
    input wire s           // Selector: 0 para A, 1 para B
);
    assign Out = s ? B : A; // Selección de salida
endmodule

testbench/mux2_4_tb.v
`timescale 1ns/1ps

module tb_mux2_4;
    reg [3:0] A;
    reg [3:0] B;
    reg s;
    wire [3:0] Out;

    // Instantiate unit under test
    mux2_4 uut(.Out(Out), .A(A), .B(B), .s(s));

    initial begin
        // Write VCD into the local vcd/ directory of the project
        $dumpfile("vcd/mux2_4_tb.vcd");
        $dumpvars(0, tb_mux2_4);
        // Keep A and B constant: A = 0, B = all ones. Vary only 's'.
        A = 4'b0000; B = 4'b1111;

        // Start with s = 0 and check Out == A
        s = 0; #10;
        if (Out !== A) $display("%0t ERROR: s=0 but Out!=A (Out=%b A=%b)", $time, Out, A);
        else $display("%0t OK: s=0 Out==A (%b)", $time, Out);

        // Switch to s = 1 and check Out == B
        s = 1; #10;
        if (Out !== B) $display("%0t ERROR: s=1 but Out!=B (Out=%b B=%b)", $time, Out, B);
        else $display("%0t OK: s=1 Out==B (%b)", $time, Out);

        // Toggle s a few times to exercise switching (inline checks)
        repeat (8) begin
            #5 s = ~s; #5;
            if (s == 0) begin
                if (Out !== A) $display("%0t ERROR: s=0 but Out!=A (Out=%b A=%b)", $time, Out, A);
                else $display("%0t OK: s=0 Out==A (%b)", $time, Out);
            end else begin
                if (Out !== B) $display("%0t ERROR: s=1 but Out!=B (Out=%b B=%b)", $time, Out, B);
                else $display("%0t OK: s=1 Out==B (%b)", $time, Out);
            end
        end

        $display("[%0t] Testbench finished", $time);
        $finish;
    end

endmodule

vcd/mux2_4_tb.vcd
$date
	Sun Oct 12 10:51:58 2025
$end
$version
	Icarus Verilog
$end
$timescale
	1ps
$end
$scope module tb_mux2_4 $end
$var wire 4 ! Out [3:0] $end
$var reg 4 " A [3:0] $end
$var reg 4 # B [3:0] $end
$var reg 1 $ s $end
$scope module uut $end
$var wire 4 % A [3:0] $end
$var wire 4 & B [3:0] $end
$var wire 1 $ s $end
$var wire 4 ' Out [3:0] $end
$upscope $end
$upscope $end
$enddefinitions $end
$comment Show the parameter values. $end
$dumpall
$end
#0
$dumpvars
b0 '
b1111 &
b0 %
0$
b1111 #
b0 "
b0 !
$end
#10000
b1111 !
b1111 '
1$
#25000
b0 !
b0 '
0$
#35000
b1111 !
b1111 '
1$
#45000
b0 !
b0 '
0$
#55000
b1111 !
b1111 '
1$
#65000
b0 !
b0 '
0$
#75000
b1111 !
b1111 '
1$
#85000
b0 !
b0 '
0$
#95000
b1111 !
b1111 '
1$
