mux4_1.v
module mux4_1(output reg out, input wire a, b, c, d, input wire [1:0] S);

always @* begin
  if(S == 2'b00)
    out = a ;
  else if(S == 2'b01)
    out = b ;
  else if(S == 2'b10)
    out = c ;
  else
    out = d ;
end
endmodule

testbench/mux4_1_tb.v
`timescale 1 ns / 10 ps

module mux4_1_tb;
    reg test_a, test_b, test_c, test_d;
    reg [1:0] test_S;
    wire test_out;

    // Instancia del módulo a testear
    mux4_1 uut(test_out, test_a, test_b, test_c, test_d, test_S);

    initial begin
        $monitor("tiempo=%0d a=%b b=%b c=%b d=%b S=%b out=%b", $time, test_a, test_b, test_c, test_d, test_S, test_out);
        $dumpfile("mux4_1_tb.vcd");
        $dumpvars;

        // vector de test 0
        test_a = 0; test_b = 0; test_c = 0; test_d = 0; test_S = 2'b00;
        #20;
        // vector de test 1
        test_a = 1; test_b = 0; test_c = 0; test_d = 0; test_S = 2'b00;
        #20;
        // vector de test 2
        test_a = 0; test_b = 1; test_c = 0; test_d = 0; test_S = 2'b01;
        #20;
        // vector de test 3
        test_a = 0; test_b = 0; test_c = 1; test_d = 0; test_S = 2'b10;
        #20;
        // vector de test 4
        test_a = 0; test_b = 0; test_c = 0; test_d = 1; test_S = 2'b11;
        #20;
        // vector de test 5
        test_a = 1; test_b = 1; test_c = 1; test_d = 1; test_S = 2'b00;
        #20;
        test_S = 2'b01;
        #20;
        test_S = 2'b10;
        #20;
        test_S = 2'b11;
        #20;
        $finish;
    end
endmodule

vcd/mux4_1_tb.vcd
$date
	Mon Sep 29 15:07:50 2025
$end
$version
	Icarus Verilog
$end
$timescale
	10ps
$end
$scope module mux4_1_tb $end
$var wire 1 ! test_out $end
$var reg 2 " test_S [1:0] $end
$var reg 1 # test_a $end
$var reg 1 $ test_b $end
$var reg 1 % test_c $end
$var reg 1 & test_d $end
$scope module uut $end
$var wire 2 ' S [1:0] $end
$var wire 1 # a $end
$var wire 1 $ b $end
$var wire 1 % c $end
$var wire 1 & d $end
$var reg 1 ! out $end
$upscope $end
$upscope $end
$enddefinitions $end
$comment Show the parameter values. $end
$dumpall
$end
#0
$dumpvars
b0 '
0&
0%
0$
0#
b0 "
0!
$end
#2000
1!
1#
#4000
b1 "
b1 '
1$
0#
#6000
b10 "
b10 '
1%
0$
#8000
b11 "
b11 '
1&
0%
#10000
b0 "
b0 '
1%
1$
1#
#12000
b1 "
b1 '
#14000
b10 "
b10 '
#16000
b11 "
b11 '
