compl1.v
// Complementador a 1 de 4 bits
// Si cpl = 1, invierte todos los bits de Inp; si cpl = 0, deja Inp sin modificar
module compl1(
    output wire [3:0] Out, // Salida: complemento a 1 o dato original
    input wire [3:0] Inp,  // Entrada de 4 bits
    input wire cpl         // Control: 1 para invertir, 0 para dejar igual
);
    assign Out = cpl ? ~Inp : Inp; // Operación de complemento a 1
endmodule

mux2_4.v
// Multiplexor 2 a 1 de 4 bits
// Selecciona entre las entradas A y B según el selector s
module mux2_4(
    output wire [3:0] Out, // Salida de 4 bits
    input wire [3:0] A,    // Entrada A
    input wire [3:0] B,    // Entrada B
    input wire s           // Selector: 0 para A, 1 para B
);
    assign Out = s ? B : A; // Selección de salida
endmodule

preprocess.v
module preprocess(output wire [3:0] AMod, output wire [3:0] BMod, input wire [3:0] A, input wire [3:0] B, input wire [2:0] Op);

    //Buses intermedios
    wire [3:0] muxAMuxB;
    wire [3:0] muxInputCPL;

    //Señales de control (driven procedurally from Op)
    reg add1Signal;
    reg op1_ASignal;
    reg op2_BSignal;
    reg cplSignal;

    // Bits individuales de Op
    wire OP2 = Op[2];
    wire OP1 = Op[1];
    wire OP0 = Op[0];

    // Logica de control establecida por la tabla de verdad
    always @(*) begin
        // defaults
        add1Signal = 1'b0;
        op1_ASignal = 1'b0;
        op2_BSignal = 1'b0;
        cplSignal = 1'b0;

        case (Op)
            3'b000: begin // A + B  : ADD1=x -> choose 0, OP1_A=1, OP2_B=1, CPL=0
                add1Signal = 1'b0; op1_ASignal = 1'b1; op2_BSignal = 1'b1; cplSignal = 1'b0;
            end
            3'b001: begin // A + 1 : ADD1=1, OP1_A=0, OP2_B=0, CPL=0
                add1Signal = 1'b1; op1_ASignal = 1'b0; op2_BSignal = 1'b0; cplSignal = 1'b0;
            end
            3'b010: begin // -A : ADD1=1, OP1_A=0, OP2_B=0, CPL=1
                add1Signal = 1'b1; op1_ASignal = 1'b0; op2_BSignal = 1'b0; cplSignal = 1'b1;
            end
            3'b011: begin // -B : ADD1=1, OP1_A=0, OP2_B=1, CPL=1
                add1Signal = 1'b1; op1_ASignal = 1'b0; op2_BSignal = 1'b1; cplSignal = 1'b1;
            end
            3'b100: begin // A & C : ADD1=x -> choose 0, OP1_A=1, OP2_B=1, CPL=0
                add1Signal = 1'b0; op1_ASignal = 1'b1; op2_BSignal = 1'b1; cplSignal = 1'b0;
            end
            3'b101: begin // A | B : ADD1=x -> choose 0, OP1_A=1, OP2_B=1, CPL=0
                add1Signal = 1'b0; op1_ASignal = 1'b1; op2_BSignal = 1'b1; cplSignal = 1'b0;
            end
            3'b110: begin // A XOR B : ADD1=x -> choose 0, OP1_A=1, OP2_B=1, CPL=0
                add1Signal = 1'b0; op1_ASignal = 1'b1; op2_BSignal = 1'b1; cplSignal = 1'b0;
            end
            3'b111: begin // ¬A : ADD1=x -> choose 0, OP1_A=1, OP2_B=x -> choose 0, CPL=x -> choose 0
                add1Signal = 1'b0; op1_ASignal = 1'b1; op2_BSignal = 1'b0; cplSignal = 1'b0;
            end
            default: begin
                add1Signal = 1'b0; op1_ASignal = 1'b0; op2_BSignal = 1'b0; cplSignal = 1'b0;
            end
        endcase
    end


    //Modulos
    //module mux2_4(output wire [3:0] Out, input wire [3:0] A, input wire [3:0] B, input wire s);
    mux2_4 muxAdd(muxAMuxB, 4'b0000, 4'b0001, add1Signal);
    mux2_4 muxOut(AMod, muxAMuxB, A, op1_ASignal);
    mux2_4 muxInput(muxInputCPL, A, B, op2_BSignal);

    //module compl1(output wire [3:0] Out, input wire [3:0] Inp, input wire cpl);
    compl1 complB(BMod, muxInputCPL, cplSignal);
endmodule

testbench/preprocess_tb.v
`timescale 1ns/1ps

module tb_preprocess;
    reg [3:0] A;
    reg [3:0] B;
    reg [2:0] Op;
    wire [3:0] AMod;
    wire [3:0] BMod;

    integer i,j,k;
    integer errors;
    integer checks;
    // signal aliases and expected regs at module scope
    wire OP2;
    wire OP1;
    wire OP0;
    reg add1Signal;
    reg op1_ASignal;
    reg op2_BSignal;
    reg cplSignal;
    reg [3:0] muxAMuxB;
    reg [3:0] AMod_exp;
    reg [3:0] muxInputCPL;
    reg [3:0] BMod_exp;

    // Instantiate unit under test
    preprocess uut(.AMod(AMod), .BMod(BMod), .A(A), .B(B), .Op(Op));

    // helpers to compute expected values (must match preprocess.v logic)
    function [3:0] expected_muxAdd(input add1);
        expected_muxAdd = add1 ? 4'b1111 : 4'b0000;
    endfunction

    function [3:0] expected_muxOut(input [3:0] muxAMuxB, input [3:0] A_val, input op1);
        expected_muxOut = op1 ? A_val : muxAMuxB;
    endfunction

    function [3:0] expected_muxInput(input [3:0] A_val, input [3:0] B_val, input op2);
        expected_muxInput = op2 ? B_val : A_val;
    endfunction

    initial begin
        $dumpfile("vcd/preprocess_tb.vcd");
        // dump only top-level I/O and results
        $dumpvars(0, tb_preprocess.A, tb_preprocess.B, tb_preprocess.Op, tb_preprocess.AMod, tb_preprocess.BMod);

        errors = 0;
        checks = 0;

        // Very simplified test: fixed inputs A and B as requested by user
        // A = 3'b001 -> represent as 4'b0001, B = 3'b010 -> 4'b0010
        A = 4'b0001;
        B = 4'b0010;

        // iterate Op only (0..7)
        for (i = 0; i < 8; i = i + 1) begin
            Op = i[2:0];

            // compute control helper signals (match preprocess logic)
            add1Signal = Op[2] | (~Op[2] & ~Op[1] & ~Op[0]);
            op1_ASignal = add1Signal;
            op2_BSignal = Op[2] | (~Op[2] & ~(Op[1] ^ Op[0]));
            cplSignal = ~Op[2] & Op[1];

            #1; // let DUT settle and record in VCD

            // compute expected values for current Op
            muxAMuxB = expected_muxAdd(add1Signal);
            AMod_exp = expected_muxOut(muxAMuxB, A, op1_ASignal);
            muxInputCPL = expected_muxInput(A, B, op2_BSignal);
            BMod_exp = cplSignal ? ~muxInputCPL : muxInputCPL;

            checks = checks + 2;
            if (AMod !== AMod_exp) begin
                $display("%0t ERROR: Op=%b A=%b B=%b AMod=%b expected=%b", $time, Op, A, B, AMod, AMod_exp);
                errors = errors + 1;
            end
            if (BMod !== BMod_exp) begin
                $display("%0t ERROR: Op=%b A=%b B=%b BMod=%b expected=%b", $time, Op, A, B, BMod, BMod_exp);
                errors = errors + 1;
            end
        end

        $display("Very simplified preprocess test finished: %0d checks, %0d errors", checks, errors);
        $finish;
    end

endmodule

vcd/preprocess_tb.vcd
$date
	Sun Oct 12 12:29:46 2025
$end
$version
	Icarus Verilog
$end
$timescale
	1ps
$end
$scope module tb_preprocess $end
$var reg 4 ! A [3:0] $end
$upscope $end
$scope module tb_preprocess $end
$var reg 4 " B [3:0] $end
$upscope $end
$scope module tb_preprocess $end
$var reg 3 # Op [2:0] $end
$upscope $end
$scope module tb_preprocess $end
$var wire 4 $ AMod [3:0] $end
$upscope $end
$scope module tb_preprocess $end
$var wire 4 % BMod [3:0] $end
$upscope $end
$enddefinitions $end
$comment Show the parameter values. $end
$dumpall
$end
#0
$dumpvars
b10 %
b1 $
b0 #
b10 "
b1 !
$end
#1000
b1 %
b1 $
b1 #
#2000
b1110 %
b10 #
#3000
b1101 %
b11 #
#4000
b10 %
b100 #
#5000
b101 #
#6000
b110 #
#7000
b1 %
b111 #
