mux4_1.v
module mux4_1(output reg out, input wire a, b, c, d, input wire [1:0] S);

always @* begin
  if(S == 2'b00)
    out = a ;
  else if(S == 2'b01)
    out = b ;
  else if(S == 2'b10)
    out = c ;
  else
    out = d ;
end
endmodule

cl.v
module cl(output wire out, input wire a, b, input wire [1:0] S);

    wire o1, o2, o3, o4;
    //module and2(output wire out, input wire a, b);
    and and1 (o1, a, b);
    //module or2(output wire out, input wire a, b);
    or or1 (o2, a, b);
    //module xor2(output wire out, input wire a, b);
    xor xor1 (o3, a, b);               
    //module not1(output wire out, input wire a);
    not not1 (o4, a);
    
    //module mux4_1(output reg out, input wire a, b, c, d, input wire [1:0] S);
    mux4_1 mux1 (out, o1, o2, o3, o4, S);

endmodule

ul4.v
module ul4(output wire[3:0] Out, input wire[3:0] A, input wire[3:0] B, input wire [1:0] S);
    //celdas logicas
    //module cl(output wire out, input wire a, b, input wire [1:0] S);
    cl cl1(Out[0], A[0], B[0], S);
    cl cl2(Out[1], A[1], B[1], S);
    cl cl3(Out[2], A[2], B[2], S);
    cl cl4(Out[3], A[3], B[3], S);
endmodule

testbench/ul4_tb.v
`timescale 1ns/1ps

module tb_ul4;
    reg [3:0] A;
    reg [3:0] B;
    reg [1:0] S;
    wire [3:0] Out;

    integer i,j,k;
    integer errors;
    integer checks;
    integer bit;

    // Instantiate unit under test
    ul4 uut(.Out(Out), .A(A), .B(B), .S(S));

    // function to compute expected bit result matching cl behavior
    function expected_cl_bit(input a, input b, input [1:0] s);
        reg o1, o2, o3, o4;
        begin
            o1 = a & b;
            o2 = a | b;
            o3 = a ^ b;
            o4 = ~a;
            case (s)
                2'b00: expected_cl_bit = o1;
                2'b01: expected_cl_bit = o2;
                2'b10: expected_cl_bit = o3;
                default: expected_cl_bit = o4;
            endcase
        end
    endfunction

    initial begin
        $dumpfile("vcd/ul4_tb.vcd");
        $dumpvars(0, tb_ul4);

        errors = 0;
        checks = 0;

        for (i = 0; i < 16; i = i + 1) begin
            A = i[3:0];
            for (j = 0; j < 16; j = j + 1) begin
                B = j[3:0];
                for (k = 0; k < 4; k = k + 1) begin
                    S = k[1:0];
                    #1;

                    // Check each bit
                    for (bit = 0; bit < 4; bit = bit + 1) begin
                        checks = checks + 1;
                        if (Out[bit] !== expected_cl_bit(A[bit], B[bit], S)) begin
                            $display("%0t ERROR: A=%b B=%b S=%b Out[%0d]=%b expected=%b", $time, A, B, S, bit, Out[bit], expected_cl_bit(A[bit], B[bit], S));
                            errors = errors + 1;
                        end
                    end
                end
            end
        end

        $display("ul4 test finished: %0d checks, %0d errors", checks, errors);
        $finish;
    end

endmodule

vcd/ul4_tb.vcd
$date
	Sun Oct 12 12:12:44 2025
$end
$version
	Icarus Verilog
$end
$timescale
	1ps
$end
$scope module tb_ul4 $end
$var wire 4 ! Out [3:0] $end
$var reg 4 " A [3:0] $end
$var reg 4 # B [3:0] $end
$var reg 2 $ S [1:0] $end
$var integer 32 % bit [31:0] $end
$var integer 32 & checks [31:0] $end
$var integer 32 ' errors [31:0] $end
$var integer 32 ( i [31:0] $end
$var integer 32 ) j [31:0] $end
$var integer 32 * k [31:0] $end
$scope function expected_cl_bit $end
$var reg 1 + a $end
$var reg 1 , b $end
$var reg 1 - o1 $end
$var reg 1 . o2 $end
$var reg 1 / o3 $end
$var reg 1 0 o4 $end
$var reg 2 1 s [1:0] $end
$upscope $end
$scope module uut $end
$var wire 4 2 A [3:0] $end
$var wire 4 3 B [3:0] $end
$var wire 2 4 S [1:0] $end
$var wire 4 5 Out [3:0] $end
$scope module cl1 $end
$var wire 2 6 S [1:0] $end
$var wire 1 7 a $end
$var wire 1 8 b $end
$var wire 1 9 o1 $end
$var wire 1 : o2 $end
$var wire 1 ; o3 $end
$var wire 1 < o4 $end
$var wire 1 = out $end
$scope module mux1 $end
$var wire 2 > S [1:0] $end
$var wire 1 9 a $end
$var wire 1 : b $end
$var wire 1 ; c $end
$var wire 1 < d $end
$var reg 1 = out $end
$upscope $end
$upscope $end
$scope module cl2 $end
$var wire 2 ? S [1:0] $end
$var wire 1 @ a $end
$var wire 1 A b $end
$var wire 1 B o1 $end
$var wire 1 C o2 $end
$var wire 1 D o3 $end
$var wire 1 E o4 $end
$var wire 1 F out $end
$scope module mux1 $end
$var wire 2 G S [1:0] $end
$var wire 1 B a $end
$var wire 1 C b $end
$var wire 1 D c $end
$var wire 1 E d $end
$var reg 1 F out $end
$upscope $end
$upscope $end
$scope module cl3 $end
$var wire 2 H S [1:0] $end
$var wire 1 I a $end
$var wire 1 J b $end
$var wire 1 K o1 $end
$var wire 1 L o2 $end
$var wire 1 M o3 $end
$var wire 1 N o4 $end
$var wire 1 O out $end
$scope module mux1 $end
$var wire 2 P S [1:0] $end
$var wire 1 K a $end
$var wire 1 L b $end
$var wire 1 M c $end
$var wire 1 N d $end
$var reg 1 O out $end
$upscope $end
$upscope $end
$scope module cl4 $end
$var wire 2 Q S [1:0] $end
$var wire 1 R a $end
$var wire 1 S b $end
$var wire 1 T o1 $end
$var wire 1 U o2 $end
$var wire 1 V o3 $end
$var wire 1 W o4 $end
$var wire 1 X out $end
$scope module mux1 $end
$var wire 2 Y S [1:0] $end
$var wire 1 T a $end
$var wire 1 U b $end
$var wire 1 V c $end
$var wire 1 W d $end
$var reg 1 X out $end
$upscope $end
$upscope $end
$upscope $end
$upscope $end
$enddefinitions $end
$comment Show the parameter values. $end
$dumpall
$end
#0
$dumpvars
b0 Y
0X
1W
0V
0U
0T
0S
0R
b0 Q
b0 P
0O
1N
0M
0L
0K
0J
0I
b0 H
b0 G
0F
1E
0D
0C
0B
0A
0@
b0 ?
b0 >
0=
1<
0;
0:
09
08
07
b0 6
b0 5
b0 4
b0 3
b0 2
bx 1
x0
x/
x.
x-
x,
x+
b0 *
b0 )
b0 (
b0 '
b0 &
bx %
b0 $
b0 #
b0 "
b0 !
$end
#1000
b1 $
b1 4
b1 6
b1 >
b1 ?
b1 G
b1 H
b1 P
b1 Q
b1 Y
b1 *
10
0/
0.
0-
0+
0,
b0 1
b100 &
b100 %
#2000
b10 $
b10 4
b10 6
b10 >
b10 ?
b10 G
b10 H
b10 P
b10 Q
b10 Y
b10 *
b1 1
b1000 &
b100 %
#3000
1=
1F
1O
b1111 !
b1111 5
1X
b11 $
b11 4
b11 6
b11 >
b11 ?
b11 G
b11 H
b11 P
b11 Q
b11 Y
b11 *
b10 1
b1100 &
b100 %
#4000
1:
1;
0=
0F
0O
b0 !
b0 5
0X
18
b0 $
b0 4
b0 6
b0 >
b0 ?
b0 G
b0 H
b0 P
b0 Q
b0 Y
b1 #
b1 3
b1 )
b0 *
b11 1
b10000 &
b100 %
#5000
b1 !
b1 5
1=
b1 $
b1 4
b1 6
b1 >
b1 ?
b1 G
b1 H
b1 P
b1 Q
b1 Y
b1 *
0/
0.
0,
b0 1
b10100 &
b100 %
#6000
b10 $
b10 4
b10 6
b10 >
b10 ?
b10 G
b10 H
b10 P
b10 Q
b10 Y
b10 *
0/
0.
0,
b1 1
b11000 &
b100 %
#7000
1F
1O
b1111 !
b1111 5
1X
b11 $
b11 4
b11 6
b11 >
b11 ?
b11 G
b11 H
b11 P
b11 Q
b11 Y
b11 *
0/
0.
0,
b10 1
b11100 &
b100 %
#8000
0:
0;
1C
1D
0=
0F
0O
b0 !
b0 5
0X
08
1A
b0 $
b0 4
b0 6
b0 >
b0 ?
b0 G
b0 H
b0 P
b0 Q
b0 Y
b10 #
b10 3
b10 )
b0 *
0/
0.
0,
b11 1
b100000 &
b100 %
#9000
b10 !
b10 5
1F
b1 $
b1 4
b1 6
b1 >
b1 ?
b1 G
b1 H
b1 P
b1 Q
b1 Y
b1 *
0/
0.
0,
b0 1
b100100 &
b100 %
#10000
b10 $
b10 4
b10 6
b10 >
b10 ?
b10 G
b10 H
b10 P
b10 Q
b10 Y
b10 *
0/
0.
0,
b1 1
b101000 &
b100 %
#11000
1=
1O
b1111 !
b1111 5
1X
b11 $
b11 4
b11 6
b11 >
b11 ?
b11 G
b11 H
b11 P
b11 Q
b11 Y
b11 *
0/
0.
0,
b10 1
b101100 &
b100 %
#12000
1:
1;
0=
0F
0O
b0 !
b0 5
0X
18
b0 $
b0 4
b0 6
b0 >
b0 ?
b0 G
b0 H
b0 P
b0 Q
b0 Y
b11 #
b11 3
b11 )
b0 *
0/
0.
0,
b11 1
b110000 &
b100 %
#13000
1=
b11 !
b11 5
1F
b1 $
b1 4
b1 6
b1 >
b1 ?
b1 G
b1 H
b1 P
b1 Q
b1 Y
b1 *
0/
0.
0,
b0 1
b110100 &
b100 %
#14000
b10 $
b10 4
b10 6
b10 >
b10 ?
b10 G
b10 H
b10 P
b10 Q
b10 Y
b10 *
0/
0.
0,
b1 1
b111000 &
b100 %
#15000
1O
b1111 !
b1111 5
1X
b11 $
b11 4
b11 6
b11 >
b11 ?
b11 G
b11 H
b11 P
b11 Q
b11 Y
b11 *
0/
0.
0,
b10 1
b111100 &
b100 %
#16000
0:
0;
0C
0D
1L
1M
0=
0F
0O
b0 !
b0 5
0X
08
0A
1J
b0 $
b0 4
b0 6
b0 >
b0 ?
b0 G
b0 H
b0 P
b0 Q
b0 Y
b100 #
b100 3
b100 )
b0 *
0/
0.
0,
b11 1
b1000000 &
b100 %
#17000
b100 !
b100 5
1O
b1 $
b1 4
b1 6
b1 >
b1 ?
b1 G
b1 H
b1 P
b1 Q
b1 Y
b1 *
0/
0.
0,
b0 1
b1000100 &
b100 %
#18000
b10 $
b10 4
b10 6
b10 >
b10 ?
b10 G
b10 H
b10 P
b10 Q
b10 Y
b10 *
0/
0.
0,
b1 1
b1001000 &
b100 %
#19000
1=
1F
b1111 !
b1111 5
1X
b11 $
b11 4
b11 6
b11 >
b11 ?
b11 G
b11 H
b11 P
b11 Q
b11 Y
b11 *
0/
0.
0,
b10 1
b1001100 &
b100 %
#20000
1:
1;
0=
0F
0O
b0 !
b0 5
0X
18
b0 $
b0 4
b0 6
b0 >
b0 ?
b0 G
b0 H
b0 P
b0 Q
b0 Y
b101 #
b101 3
b101 )
b0 *
0/
0.
0,
b11 1
b1010000 &
b100 %
#21000
1=
b101 !
b101 5
1O
b1 $
b1 4
b1 6
b1 >
b1 ?
b1 G
b1 H
b1 P
b1 Q
b1 Y
b1 *
0/
0.
0,
b0 1
b1010100 &
b100 %
#22000
b10 $
b10 4
b10 6
b10 >
b10 ?
b10 G
b10 H
b10 P
b10 Q
b10 Y
b10 *
0/
0.
0,
b1 1
b1011000 &
b100 %
#23000
1F
b1111 !
b1111 5
1X
b11 $
b11 4
b11 6
b11 >
b11 ?
b11 G
b11 H
b11 P
b11 Q
b11 Y
b11 *
0/
0.
0,
b10 1
b1011100 &
b100 %
#24000
0:
0;
1C
1D
0=
0F
0O
b0 !
b0 5
0X
08
1A
b0 $
b0 4
b0 6
b0 >
b0 ?
b0 G
b0 H
b0 P
b0 Q
b0 Y
b110 #
b110 3
b110 )
b0 *
0/
0.
0,
b11 1
b1100000 &
b100 %
#25000
1F
b110 !
b110 5
1O
b1 $
b1 4
b1 6
b1 >
b1 ?
b1 G
b1 H
b1 P
b1 Q
b1 Y
b1 *
0/
0.
0,
b0 1
b1100100 &
b100 %
#26000
b10 $
b10 4
b10 6
b10 >
b10 ?
b10 G
b10 H
b10 P
b10 Q
b10 Y
b10 *
0/
0.
0,
b1 1
b1101000 &
b100 %
#27000
1=
b1111 !
b1111 5
1X
b11 $
b11 4
b11 6
b11 >
b11 ?
b11 G
b11 H
b11 P
b11 Q
b11 Y
b11 *
0/
0.
0,
b10 1
b1101100 &
b100 %
#28000
1:
1;
0=
0F
0O
b0 !
b0 5
0X
18
b0 $
b0 4
b0 6
b0 >
b0 ?
b0 G
b0 H
b0 P
b0 Q
b0 Y
b111 #
b111 3
b111 )
b0 *
0/
0.
0,
b11 1
b1110000 &
b100 %
#29000
1=
1F
b111 !
b111 5
1O
b1 $
b1 4
b1 6
b1 >
b1 ?
b1 G
b1 H
b1 P
b1 Q
b1 Y
b1 *
0/
0.
0,
b0 1
b1110100 &
b100 %
#30000
b10 $
b10 4
b10 6
b10 >
b10 ?
b10 G
b10 H
b10 P
b10 Q
b10 Y
b10 *
0/
0.
0,
b1 1
b1111000 &
b100 %
#31000
b1111 !
b1111 5
1X
b11 $
b11 4
b11 6
b11 >
b11 ?
b11 G
b11 H
b11 P
b11 Q
b11 Y
b11 *
0/
0.
0,
b10 1
b1111100 &
b100 %
#32000
0:
0;
0C
0D
0L
0M
1U
1V
0=
0F
0O
b0 !
b0 5
0X
08
0A
0J
1S
b0 $
b0 4
b0 6
b0 >
b0 ?
b0 G
b0 H
b0 P
b0 Q
b0 Y
b1000 #
b1000 3
b1000 )
b0 *
0/
0.
0,
b11 1
b10000000 &
b100 %
#33000
b1000 !
b1000 5
1X
b1 $
b1 4
b1 6
b1 >
b1 ?
b1 G
b1 H
b1 P
b1 Q
b1 Y
b1 *
1/
1.
1,
b0 1
b10000100 &
b100 %
#34000
b10 $
b10 4
b10 6
b10 >
b10 ?
b10 G
b10 H
b10 P
b10 Q
b10 Y
b10 *
1/
1.
1,
b1 1
b10001000 &
b100 %
#35000
1=
1F
b1111 !
b1111 5
1O
b11 $
b11 4
b11 6
b11 >
b11 ?
b11 G
b11 H
b11 P
b11 Q
b11 Y
b11 *
1/
1.
1,
b10 1
b10001100 &
b100 %
#36000
1:
1;
0=
0F
0O
b0 !
b0 5
0X
18
b0 $
b0 4
b0 6
b0 >
b0 ?
b0 G
b0 H
b0 P
b0 Q
b0 Y
b1001 #
b1001 3
b1001 )
b0 *
1/
1.
1,
b11 1
b10010000 &
b100 %
#37000
1=
b1001 !
b1001 5
1X
b1 $
b1 4
b1 6
b1 >
b1 ?
b1 G
b1 H
b1 P
b1 Q
b1 Y
b1 *
1/
1.
1,
b0 1
b10010100 &
b100 %
#38000
b10 $
b10 4
b10 6
b10 >
b10 ?
b10 G
b10 H
b10 P
b10 Q
b10 Y
b10 *
1/
1.
1,
b1 1
b10011000 &
b100 %
#39000
1F
b1111 !
b1111 5
1O
b11 $
b11 4
b11 6
b11 >
b11 ?
b11 G
b11 H
b11 P
b11 Q
b11 Y
b11 *
1/
1.
1,
b10 1
b10011100 &
b100 %
#40000
0:
0;
1C
1D
0=
0F
0O
b0 !
b0 5
0X
08
1A
b0 $
b0 4
b0 6
b0 >
b0 ?
b0 G
b0 H
b0 P
b0 Q
b0 Y
b1010 #
b1010 3
b1010 )
b0 *
1/
1.
1,
b11 1
b10100000 &
b100 %
#41000
1F
b1010 !
b1010 5
1X
b1 $
b1 4
b1 6
b1 >
b1 ?
b1 G
b1 H
b1 P
b1 Q
b1 Y
b1 *
1/
1.
1,
b0 1
b10100100 &
b100 %
#42000
b10 $
b10 4
b10 6
b10 >
b10 ?
b10 G
b10 H
b10 P
b10 Q
b10 Y
b10 *
1/
1.
1,
b1 1
b10101000 &
b100 %
#43000
1=
b1111 !
b1111 5
1O
b11 $
b11 4
b11 6
b11 >
b11 ?
b11 G
b11 H
b11 P
b11 Q
b11 Y
b11 *
1/
1.
1,
b10 1
b10101100 &
b100 %
#44000
1:
1;
0=
0F
0O
b0 !
b0 5
0X
18
b0 $
b0 4
b0 6
b0 >
b0 ?
b0 G
b0 H
b0 P
b0 Q
b0 Y
b1011 #
b1011 3
b1011 )
b0 *
1/
1.
1,
b11 1
b10110000 &
b100 %
#45000
1=
1F
b1011 !
b1011 5
1X
b1 $
b1 4
b1 6
b1 >
b1 ?
b1 G
b1 H
b1 P
b1 Q
b1 Y
b1 *
1/
1.
1,
b0 1
b10110100 &
b100 %
#46000
b10 $
b10 4
b10 6
b10 >
b10 ?
b10 G
b10 H
b10 P
b10 Q
b10 Y
b10 *
1/
1.
1,
b1 1
b10111000 &
b100 %
#47000
b1111 !
b1111 5
1O
b11 $
b11 4
b11 6
b11 >
b11 ?
b11 G
b11 H
b11 P
b11 Q
b11 Y
b11 *
1/
1.
1,
b10 1
b10111100 &
b100 %
#48000
0:
0;
0C
0D
1L
1M
0=
0F
0O
b0 !
b0 5
0X
08
0A
1J
b0 $
b0 4
b0 6
b0 >
b0 ?
b0 G
b0 H
b0 P
b0 Q
b0 Y
b1100 #
b1100 3
b1100 )
b0 *
1/
1.
1,
b11 1
b11000000 &
b100 %
#49000
1O
b1100 !
b1100 5
1X
b1 $
b1 4
b1 6
b1 >
b1 ?
b1 G
b1 H
b1 P
b1 Q
b1 Y
b1 *
1/
1.
1,
b0 1
b11000100 &
b100 %
#50000
b10 $
b10 4
b10 6
b10 >
b10 ?
b10 G
b10 H
b10 P
b10 Q
b10 Y
b10 *
1/
1.
1,
b1 1
b11001000 &
b100 %
#51000
1=
b1111 !
b1111 5
1F
b11 $
b11 4
b11 6
b11 >
b11 ?
b11 G
b11 H
b11 P
b11 Q
b11 Y
b11 *
1/
1.
1,
b10 1
b11001100 &
b100 %
#52000
1:
1;
0=
0F
0O
b0 !
b0 5
0X
18
b0 $
b0 4
b0 6
b0 >
b0 ?
b0 G
b0 H
b0 P
b0 Q
b0 Y
b1101 #
b1101 3
b1101 )
b0 *
1/
1.
1,
b11 1
b11010000 &
b100 %
#53000
1=
1O
b1101 !
b1101 5
1X
b1 $
b1 4
b1 6
b1 >
b1 ?
b1 G
b1 H
b1 P
b1 Q
b1 Y
b1 *
1/
1.
1,
b0 1
b11010100 &
b100 %
#54000
b10 $
b10 4
b10 6
b10 >
b10 ?
b10 G
b10 H
b10 P
b10 Q
b10 Y
b10 *
1/
1.
1,
b1 1
b11011000 &
b100 %
#55000
b1111 !
b1111 5
1F
b11 $
b11 4
b11 6
b11 >
b11 ?
b11 G
b11 H
b11 P
b11 Q
b11 Y
b11 *
1/
1.
1,
b10 1
b11011100 &
b100 %
#56000
0:
0;
1C
1D
0=
0F
0O
b0 !
b0 5
0X
08
1A
b0 $
b0 4
b0 6
b0 >
b0 ?
b0 G
b0 H
b0 P
b0 Q
b0 Y
b1110 #
b1110 3
b1110 )
b0 *
1/
1.
1,
b11 1
b11100000 &
b100 %
#57000
1F
1O
b1110 !
b1110 5
1X
b1 $
b1 4
b1 6
b1 >
b1 ?
b1 G
b1 H
b1 P
b1 Q
b1 Y
b1 *
1/
1.
1,
b0 1
b11100100 &
b100 %
#58000
b10 $
b10 4
b10 6
b10 >
b10 ?
b10 G
b10 H
b10 P
b10 Q
b10 Y
b10 *
1/
1.
1,
b1 1
b11101000 &
b100 %
#59000
b1111 !
b1111 5
1=
b11 $
b11 4
b11 6
b11 >
b11 ?
b11 G
b11 H
b11 P
b11 Q
b11 Y
b11 *
1/
1.
1,
b10 1
b11101100 &
b100 %
#60000
1:
1;
0=
0F
0O
b0 !
b0 5
0X
18
b0 $
b0 4
b0 6
b0 >
b0 ?
b0 G
b0 H
b0 P
b0 Q
b0 Y
b1111 #
b1111 3
b1111 )
b0 *
1/
1.
1,
b11 1
b11110000 &
b100 %
#61000
1=
1F
1O
b1111 !
b1111 5
1X
b1 $
b1 4
b1 6
b1 >
b1 ?
b1 G
b1 H
b1 P
b1 Q
b1 Y
b1 *
b0 1
b11110100 &
b100 %
#62000
b10 $
b10 4
b10 6
b10 >
b10 ?
b10 G
b10 H
b10 P
b10 Q
b10 Y
b10 *
b1 1
b11111000 &
b100 %
#63000
b11 $
b11 4
b11 6
b11 >
b11 ?
b11 G
b11 H
b11 P
b11 Q
b11 Y
b11 *
b10 1
b11111100 &
b100 %
#64000
0C
0D
0L
0M
0U
0V
0<
0=
0F
0O
b0 !
b0 5
0X
08
0A
0J
0S
17
b0 $
b0 4
b0 6
b0 >
b0 ?
b0 G
b0 H
b0 P
b0 Q
b0 Y
b0 #
b0 3
b1 "
b1 2
b1 (
b0 )
b0 *
b11 1
b100000000 &
b100 %
#65000
b1 !
b1 5
1=
b1 $
b1 4
b1 6
b1 >
b1 ?
b1 G
b1 H
b1 P
b1 Q
b1 Y
b1 *
0/
0.
10
0+
0,
b0 1
b100000100 &
b100 %
#66000
b10 $
b10 4
b10 6
b10 >
b10 ?
b10 G
b10 H
b10 P
b10 Q
b10 Y
b10 *
10
0/
0.
0+
b1 1
b100001000 &
b100 %
#67000
0=
1F
1O
b1110 !
b1110 5
1X
b11 $
b11 4
b11 6
b11 >
b11 ?
b11 G
b11 H
b11 P
b11 Q
b11 Y
b11 *
10
0/
0.
0+
b10 1
b100001100 &
b100 %
#68000
1=
19
0;
0F
0O
b1 !
b1 5
0X
18
b0 $
b0 4
b0 6
b0 >
b0 ?
b0 G
b0 H
b0 P
b0 Q
b0 Y
b1 #
b1 3
b1 )
b0 *
10
0/
0.
0+
b11 1
b100010000 &
b100 %
#69000
b1 $
b1 4
b1 6
b1 >
b1 ?
b1 G
b1 H
b1 P
b1 Q
b1 Y
b1 *
10
0.
0-
0+
0,
b0 1
b100010100 &
b100 %
#70000
b0 !
b0 5
0=
b10 $
b10 4
b10 6
b10 >
b10 ?
b10 G
b10 H
b10 P
b10 Q
b10 Y
b10 *
10
0.
0-
0+
0,
b1 1
b100011000 &
b100 %
#71000
1F
1O
b1110 !
b1110 5
1X
b11 $
b11 4
b11 6
b11 >
b11 ?
b11 G
b11 H
b11 P
b11 Q
b11 Y
b11 *
10
0.
0-
0+
0,
b10 1
b100011100 &
b100 %
#72000
09
1;
1C
1D
0=
0F
0O
b0 !
b0 5
0X
08
1A
b0 $
b0 4
b0 6
b0 >
b0 ?
b0 G
b0 H
b0 P
b0 Q
b0 Y
b10 #
b10 3
b10 )
b0 *
10
0.
0-
0+
0,
b11 1
b100100000 &
b100 %
#73000
1=
b11 !
b11 5
1F
b1 $
b1 4
b1 6
b1 >
b1 ?
b1 G
b1 H
b1 P
b1 Q
b1 Y
b1 *
0,
10
0/
0.
0+
b0 1
b100100100 &
b100 %
#74000
b10 $
b10 4
b10 6
b10 >
b10 ?
b10 G
b10 H
b10 P
b10 Q
b10 Y
b10 *
0,
10
0/
0.
0+
b1 1
b100101000 &
b100 %
#75000
0=
1O
b1110 !
b1110 5
1X
b11 $
b11 4
b11 6
b11 >
b11 ?
b11 G
b11 H
b11 P
b11 Q
b11 Y
b11 *
0,
10
0/
0.
0+
b10 1
b100101100 &
b100 %
#76000
1=
19
0;
0F
0O
b1 !
b1 5
0X
18
b0 $
b0 4
b0 6
b0 >
b0 ?
b0 G
b0 H
b0 P
b0 Q
b0 Y
b11 #
b11 3
b11 )
b0 *
0,
10
0/
0.
0+
b11 1
b100110000 &
b100 %
#77000
b11 !
b11 5
1F
b1 $
b1 4
b1 6
b1 >
b1 ?
b1 G
b1 H
b1 P
b1 Q
b1 Y
b1 *
0/
10
0.
0-
0+
0,
b0 1
b100110100 &
b100 %
#78000
b10 !
b10 5
0=
b10 $
b10 4
b10 6
b10 >
b10 ?
b10 G
b10 H
b10 P
b10 Q
b10 Y
b10 *
0/
10
0.
0-
0+
0,
b1 1
b100111000 &
b100 %
#79000
1O
b1110 !
b1110 5
1X
b11 $
b11 4
b11 6
b11 >
b11 ?
b11 G
b11 H
b11 P
b11 Q
b11 Y
b11 *
0/
10
0.
0-
0+
0,
b10 1
b100111100 &
b100 %
#80000
09
1;
0C
0D
1L
1M
0=
0F
0O
b0 !
b0 5
0X
08
0A
1J
b0 $
b0 4
b0 6
b0 >
b0 ?
b0 G
b0 H
b0 P
b0 Q
b0 Y
b100 #
b100 3
b100 )
b0 *
0/
10
0.
0-
0+
0,
b11 1
b101000000 &
b100 %
#81000
1=
b101 !
b101 5
1O
b1 $
b1 4
b1 6
b1 >
b1 ?
b1 G
b1 H
b1 P
b1 Q
b1 Y
b1 *
0,
10
0/
0.
0+
b0 1
b101000100 &
b100 %
#82000
b10 $
b10 4
b10 6
b10 >
b10 ?
b10 G
b10 H
b10 P
b10 Q
b10 Y
b10 *
0,
10
0/
0.
0+
b1 1
b101001000 &
b100 %
#83000
0=
1F
b1110 !
b1110 5
1X
b11 $
b11 4
b11 6
b11 >
b11 ?
b11 G
b11 H
b11 P
b11 Q
b11 Y
b11 *
0,
10
0/
0.
0+
b10 1
b101001100 &
b100 %
#84000
1=
19
0;
0F
0O
b1 !
b1 5
0X
18
b0 $
b0 4
b0 6
b0 >
b0 ?
b0 G
b0 H
b0 P
b0 Q
b0 Y
b101 #
b101 3
b101 )
b0 *
0,
10
0/
0.
0+
b11 1
b101010000 &
b100 %
#85000
b101 !
b101 5
1O
b1 $
b1 4
b1 6
b1 >
b1 ?
b1 G
b1 H
b1 P
b1 Q
b1 Y
b1 *
0/
10
0.
0-
0+
0,
b0 1
b101010100 &
b100 %
#86000
b100 !
b100 5
0=
b10 $
b10 4
b10 6
b10 >
b10 ?
b10 G
b10 H
b10 P
b10 Q
b10 Y
b10 *
0/
10
0.
0-
0+
0,
b1 1
b101011000 &
b100 %
#87000
1F
b1110 !
b1110 5
1X
b11 $
b11 4
b11 6
b11 >
b11 ?
b11 G
b11 H
b11 P
b11 Q
b11 Y
b11 *
0/
10
0.
0-
0+
0,
b10 1
b101011100 &
b100 %
#88000
09
1;
1C
1D
0=
0F
0O
b0 !
b0 5
0X
08
1A
b0 $
b0 4
b0 6
b0 >
b0 ?
b0 G
b0 H
b0 P
b0 Q
b0 Y
b110 #
b110 3
b110 )
b0 *
0/
10
0.
0-
0+
0,
b11 1
b101100000 &
b100 %
#89000
1=
1F
b111 !
b111 5
1O
b1 $
b1 4
b1 6
b1 >
b1 ?
b1 G
b1 H
b1 P
b1 Q
b1 Y
b1 *
0,
10
0/
0.
0+
b0 1
b101100100 &
b100 %
#90000
b10 $
b10 4
b10 6
b10 >
b10 ?
b10 G
b10 H
b10 P
b10 Q
b10 Y
b10 *
0,
10
0/
0.
0+
b1 1
b101101000 &
b100 %
#91000
0=
b1110 !
b1110 5
1X
b11 $
b11 4
b11 6
b11 >
b11 ?
b11 G
b11 H
b11 P
b11 Q
b11 Y
b11 *
0,
10
0/
0.
0+
b10 1
b101101100 &
b100 %
#92000
1=
19
0;
0F
0O
b1 !
b1 5
0X
18
b0 $
b0 4
b0 6
b0 >
b0 ?
b0 G
b0 H
b0 P
b0 Q
b0 Y
b111 #
b111 3
b111 )
b0 *
0,
10
0/
0.
0+
b11 1
b101110000 &
b100 %
#93000
1F
b111 !
b111 5
1O
b1 $
b1 4
b1 6
b1 >
b1 ?
b1 G
b1 H
b1 P
b1 Q
b1 Y
b1 *
0/
10
0.
0-
0+
0,
b0 1
b101110100 &
b100 %
#94000
b110 !
b110 5
0=
b10 $
b10 4
b10 6
b10 >
b10 ?
b10 G
b10 H
b10 P
b10 Q
b10 Y
b10 *
0/
10
0.
0-
0+
0,
b1 1
b101111000 &
b100 %
#95000
b1110 !
b1110 5
1X
b11 $
b11 4
b11 6
b11 >
b11 ?
b11 G
b11 H
b11 P
b11 Q
b11 Y
b11 *
0/
10
0.
0-
0+
0,
b10 1
b101111100 &
b100 %
#96000
09
1;
0C
0D
0L
0M
1U
1V
0=
0F
0O
b0 !
b0 5
0X
08
0A
0J
1S
b0 $
b0 4
b0 6
b0 >
b0 ?
b0 G
b0 H
b0 P
b0 Q
b0 Y
b1000 #
b1000 3
b1000 )
b0 *
0/
10
0.
0-
0+
0,
b11 1
b110000000 &
b100 %
#97000
1=
b1001 !
b1001 5
1X
b1 $
b1 4
b1 6
b1 >
b1 ?
b1 G
b1 H
b1 P
b1 Q
b1 Y
b1 *
1,
10
1/
1.
0+
b0 1
b110000100 &
b100 %
#98000
b10 $
b10 4
b10 6
b10 >
b10 ?
b10 G
b10 H
b10 P
b10 Q
b10 Y
b10 *
1/
1.
10
0+
1,
b1 1
b110001000 &
b100 %
#99000
0=
1F
b1110 !
b1110 5
1O
b11 $
b11 4
b11 6
b11 >
b11 ?
b11 G
b11 H
b11 P
b11 Q
b11 Y
b11 *
1/
1.
10
0+
1,
b10 1
b110001100 &
b100 %
#100000
1=
19
0;
0F
0O
b1 !
b1 5
0X
18
b0 $
b0 4
b0 6
b0 >
b0 ?
b0 G
b0 H
b0 P
b0 Q
b0 Y
b1001 #
b1001 3
b1001 )
b0 *
1/
1.
10
0+
1,
b11 1
b110010000 &
b100 %
#101000
b1001 !
b1001 5
1X
b1 $
b1 4
b1 6
b1 >
b1 ?
b1 G
b1 H
b1 P
b1 Q
b1 Y
b1 *
1.
1,
10
1/
0-
0+
b0 1
b110010100 &
b100 %
#102000
b1000 !
b1000 5
0=
b10 $
b10 4
b10 6
b10 >
b10 ?
b10 G
b10 H
b10 P
b10 Q
b10 Y
b10 *
1.
1,
10
1/
0-
0+
b1 1
b110011000 &
b100 %
#103000
1F
b1110 !
b1110 5
1O
b11 $
b11 4
b11 6
b11 >
b11 ?
b11 G
b11 H
b11 P
b11 Q
b11 Y
b11 *
1.
1,
10
1/
0-
0+
b10 1
b110011100 &
b100 %
#104000
09
1;
1C
1D
0=
0F
0O
b0 !
b0 5
0X
08
1A
b0 $
b0 4
b0 6
b0 >
b0 ?
b0 G
b0 H
b0 P
b0 Q
b0 Y
b1010 #
b1010 3
b1010 )
b0 *
1.
1,
10
1/
0-
0+
b11 1
b110100000 &
b100 %
#105000
1=
1F
b1011 !
b1011 5
1X
b1 $
b1 4
b1 6
b1 >
b1 ?
b1 G
b1 H
b1 P
b1 Q
b1 Y
b1 *
1/
1.
10
0+
1,
b0 1
b110100100 &
b100 %
#106000
b10 $
b10 4
b10 6
b10 >
b10 ?
b10 G
b10 H
b10 P
b10 Q
b10 Y
b10 *
1/
1.
10
0+
1,
b1 1
b110101000 &
b100 %
#107000
0=
b1110 !
b1110 5
1O
b11 $
b11 4
b11 6
b11 >
b11 ?
b11 G
b11 H
b11 P
b11 Q
b11 Y
b11 *
1/
1.
10
0+
1,
b10 1
b110101100 &
b100 %
